forcode/__init__.py
forcode/docstring.py
forcode/main.py
forcode/readme.py
forcode-0.1.6.dist-info/METADATA
forcode-0.1.6.dist-info/WHEEL
forcode-0.1.6.dist-info/entry_points.txt
forcode-0.1.6.dist-info/top_level.txt
forcode-0.1.6.dist-info/RECORD
