Metadata-Version: 2.4
Name: forcode
Version: 0.1.6
Summary: Generate recursive README.md documentation for Python modules using generative AI.
Home-page: https://github.com/yourusername/forcode
Author: James
Author-email: support@forcode.ai
License: Proprietary
Classifier: License :: Other/Proprietary License
Classifier: Programming Language :: Python :: 3
Classifier: Programming Language :: Python :: 3.12
Classifier: Operating System :: OS Independent
Requires-Python: >=3.8
Requires-Dist: forgen>=0.1.5
Requires-Dist: openai>=1.73
Dynamic: author
Dynamic: author-email
Dynamic: classifier
Dynamic: description
Dynamic: description-content-type
Dynamic: home-page
Dynamic: license
Dynamic: requires-dist
Dynamic: requires-python
Dynamic: summary
